opticallyshallowdeep/__init__.py
opticallyshallowdeep/check_transpose.py
opticallyshallowdeep/cloud_mask.py
opticallyshallowdeep/find_epsg.py
opticallyshallowdeep/make_multiband_image.py
opticallyshallowdeep/make_vertical_strips.py
opticallyshallowdeep/netcdf_to_multiband_geotiff.py
opticallyshallowdeep/parse_string.py
opticallyshallowdeep/process_as_strips.py
opticallyshallowdeep/run.py
opticallyshallowdeep/write_georef_image.py
opticallyshallowdeep/models/SR.h5
opticallyshallowdeep/models/TOA.h5
opticallyshallowdeep-1.2.3.dist-info/licenses/LICENSE
opticallyshallowdeep-1.2.3.dist-info/METADATA
opticallyshallowdeep-1.2.3.dist-info/WHEEL
opticallyshallowdeep-1.2.3.dist-info/top_level.txt
opticallyshallowdeep-1.2.3.dist-info/RECORD
