Metadata-Version: 2.4
Name: opticallyshallowdeep
Version: 1.2.3
Summary: Identify optically shallow and deep waters in satellite imagery
Author: Yulun Wu
Author-email: yulunwu8@gmail.com
Classifier: Programming Language :: Python :: 3
Requires-Python: >=3.8
License-File: LICENSE
Requires-Dist: geopandas
Requires-Dist: rasterio==1.3.9
Requires-Dist: tifffile==2023.8.12
Requires-Dist: netCDF4
Requires-Dist: pyproj
Requires-Dist: joblib
Requires-Dist: scipy
Requires-Dist: matplotlib
Requires-Dist: imagecodecs
Requires-Dist: tensorflow
Dynamic: author
Dynamic: author-email
Dynamic: classifier
Dynamic: description
Dynamic: description-content-type
Dynamic: license-file
Dynamic: requires-dist
Dynamic: requires-python
Dynamic: summary
